mocap_mdc_tracking/ViTPose/__init__.py
mocap_mdc_tracking/ViTPose/configs/_base_/datasets/300w.py
mocap_mdc_tracking/ViTPose/configs/_base_/datasets/aflw.py
mocap_mdc_tracking/ViTPose/configs/_base_/datasets/aic.py
mocap_mdc_tracking/ViTPose/configs/_base_/datasets/aic_info.py
mocap_mdc_tracking/ViTPose/configs/_base_/datasets/animalpose.py
mocap_mdc_tracking/ViTPose/configs/_base_/datasets/ap10k.py
mocap_mdc_tracking/ViTPose/configs/_base_/datasets/ap10k_info.py
mocap_mdc_tracking/ViTPose/configs/_base_/datasets/atrw.py
mocap_mdc_tracking/ViTPose/configs/_base_/datasets/coco.py
mocap_mdc_tracking/ViTPose/configs/_base_/datasets/coco_wholebody.py
mocap_mdc_tracking/ViTPose/configs/_base_/datasets/coco_wholebody_face.py
mocap_mdc_tracking/ViTPose/configs/_base_/datasets/coco_wholebody_hand.py
mocap_mdc_tracking/ViTPose/configs/_base_/datasets/coco_wholebody_info.py
mocap_mdc_tracking/ViTPose/configs/_base_/datasets/cofw.py
mocap_mdc_tracking/ViTPose/configs/_base_/datasets/crowdpose.py
mocap_mdc_tracking/ViTPose/configs/_base_/datasets/deepfashion_full.py
mocap_mdc_tracking/ViTPose/configs/_base_/datasets/deepfashion_lower.py
mocap_mdc_tracking/ViTPose/configs/_base_/datasets/deepfashion_upper.py
mocap_mdc_tracking/ViTPose/configs/_base_/datasets/fly.py
mocap_mdc_tracking/ViTPose/configs/_base_/datasets/freihand2d.py
mocap_mdc_tracking/ViTPose/configs/_base_/datasets/h36m.py
mocap_mdc_tracking/ViTPose/configs/_base_/datasets/halpe.py
mocap_mdc_tracking/ViTPose/configs/_base_/datasets/horse10.py
mocap_mdc_tracking/ViTPose/configs/_base_/datasets/interhand2d.py
mocap_mdc_tracking/ViTPose/configs/_base_/datasets/interhand3d.py
mocap_mdc_tracking/ViTPose/configs/_base_/datasets/jhmdb.py
mocap_mdc_tracking/ViTPose/configs/_base_/datasets/locust.py
mocap_mdc_tracking/ViTPose/configs/_base_/datasets/macaque.py
mocap_mdc_tracking/ViTPose/configs/_base_/datasets/mhp.py
mocap_mdc_tracking/ViTPose/configs/_base_/datasets/moveai29.py
mocap_mdc_tracking-1.12.4.dist-info/METADATA
mocap_mdc_tracking-1.12.4.dist-info/WHEEL
mocap_mdc_tracking-1.12.4.dist-info/RECORD
