Metadata-Version: 2.1
Name: mocap-mdc-tracking
Version: 1.12.4
Summary: 
Keywords: MotionOps,Moveai
Author: move.ai
Author-email: info@move.ai
Requires-Python: >=3.10,<3.13
Classifier: Programming Language :: Python :: 3
Classifier: Programming Language :: Python :: 3.10
Classifier: Programming Language :: Python :: 3.11
Classifier: Programming Language :: Python :: 3.12
Requires-Dist: filterpy (>=1.4.5,<2.0.0)
Requires-Dist: json-tricks (>=3.17.1,<4.0.0)
Requires-Dist: mmcv-full (==1.7.1)
Requires-Dist: mocap-base (>=2.0.1,<3.0.0)
Requires-Dist: mocap-pose-2d (>=2.2.0,<3.0.0)
Requires-Dist: mocap_settings (>=1.6.9,<2.0.0)
Requires-Dist: nvidia-dali-cuda120 (==1.38.0)
Requires-Dist: ortools
Requires-Dist: timm (>=0.9.2,<0.10.0)
Requires-Dist: ultralytics (>=8.3.163,<9.0.0)
Requires-Dist: xtcocotools (==1.13)
